<?xml version="1.0" encoding="UTF-8"?>
<LearningStandards>
  <LearningStandardItem xml:lang="en" RefID="3639C586FB844ED3AD7D4232451C44F1">
    <RefURI>http://corestandards.org/Math/Content/6/EE/A/2/b/</RefURI>
    <StandardHierarchyLevel>
      <number>8</number>
      <description>Component</description>
    </StandardHierarchyLevel>
    <StatementCodes>
      <StatementCode>CCSS.Math.Content.6.EE.A.2b</StatementCode>
    </StatementCodes>
    <Statements>
      <Statement>Identify parts of an expression using mathematical terms (sum, term, product, factor, quotient, coefficient); view one or more parts of an expression as a single entity. &lt;i&gt;For example, describe the expression 2 (8 + 7) as a product of two factors; view (8 + 7) as both a single entity and a sum of two terms&lt;/i&gt;.</Statement>
    </Statements>
    <GradeLevels>
      <GradeLevel>06</GradeLevel>
    </GradeLevels>
    <LearningStandardDocumentRefId>B62C1C106873438AA0126760075A65A3</LearningStandardDocumentRefId>
    <RelatedLearningStandardItems>
      <LearningStandardItemRefId RelationshipType="childOf">F78ACD4FA2D74173998D2EA26FBA1E1B</LearningStandardItemRefId>
    </RelatedLearningStandardItems>
  </LearningStandardItem>
</LearningStandards>
