<?xml version="1.0" encoding="UTF-8"?>
<LearningStandards>
  <LearningStandardItem xml:lang="en" RefID="48506CB1948147B0890BD73B816C81D4">
    <RefURI>http://corestandards.org/Math/Content/8/EE/A/1/</RefURI>
    <StandardHierarchyLevel>
      <number>7</number>
      <description>Standard</description>
    </StandardHierarchyLevel>
    <StatementCodes>
      <StatementCode>CCSS.Math.Content.8.EE.A.1</StatementCode>
    </StatementCodes>
    <Statements>
      <Statement>Know and apply the properties of integer exponents to generate equivalent numerical expressions. For example, 3&lt;sup&gt;2&lt;/sup&gt;&amp;nbsp;&amp;times;&amp;nbsp;3&lt;sup&gt;&amp;ndash;5&lt;/sup&gt; = 3&lt;sup&gt;&amp;ndash;3&lt;/sup&gt; = 1/3&lt;sup&gt;3&lt;/sup&gt; = 1/27.</Statement>
    </Statements>
    <GradeLevels>
      <GradeLevel>08</GradeLevel>
    </GradeLevels>
    <LearningStandardDocumentRefId>B62C1C106873438AA0126760075A65A3</LearningStandardDocumentRefId>
    <RelatedLearningStandardItems>
      <LearningStandardItemRefId RelationshipType="childOf">42D43D973FEF4A028D2AEAC7151A01DB</LearningStandardItemRefId>
    </RelatedLearningStandardItems>
  </LearningStandardItem>
  <LearningStandardItem xml:lang="en" RefID="5179CBDD896D4FD2973CDDAEC393C948">
    <RefURI>http://corestandards.org/Math/Content/8/EE/A/2/</RefURI>
    <StandardHierarchyLevel>
      <number>7</number>
      <description>Standard</description>
    </StandardHierarchyLevel>
    <StatementCodes>
      <StatementCode>CCSS.Math.Content.8.EE.A.2</StatementCode>
    </StatementCodes>
    <Statements>
      <Statement>Use square root and cube root symbols to represent solutions to equations of the form &lt;i&gt;x&lt;/i&gt;&lt;sup&gt;2&lt;/sup&gt; = &lt;i&gt;p&lt;/i&gt; and &lt;i&gt;x&lt;/i&gt;&lt;sup&gt;3&lt;/sup&gt; = p, where &lt;i&gt;p&lt;/i&gt; is a positive rational number. Evaluate square roots of small perfect squares and cube roots of small perfect cubes. Know that &amp;radic;2 is irrational.</Statement>
    </Statements>
    <GradeLevels>
      <GradeLevel>08</GradeLevel>
    </GradeLevels>
    <LearningStandardDocumentRefId>B62C1C106873438AA0126760075A65A3</LearningStandardDocumentRefId>
    <RelatedLearningStandardItems>
      <LearningStandardItemRefId RelationshipType="childOf">42D43D973FEF4A028D2AEAC7151A01DB</LearningStandardItemRefId>
    </RelatedLearningStandardItems>
  </LearningStandardItem>
  <LearningStandardItem xml:lang="en" RefID="0FC0B4EB2CD94EEA97757C7E474A4609">
    <RefURI>http://corestandards.org/Math/Content/8/EE/A/3/</RefURI>
    <StandardHierarchyLevel>
      <number>7</number>
      <description>Standard</description>
    </StandardHierarchyLevel>
    <StatementCodes>
      <StatementCode>CCSS.Math.Content.8.EE.A.3</StatementCode>
    </StatementCodes>
    <Statements>
      <Statement>Use numbers expressed in the form of a single digit times an integer power of 10 to estimate very large or very small quantities, and to express how many times as much one is than the other. &lt;em&gt;For example, estimate the population of the United States as 3 times 10&lt;sup&gt;8&lt;/sup&gt; and the population of the world as 7 times 10&lt;sup&gt;9&lt;/sup&gt;, and determine that the world population is more than 20 times larger&lt;/em&gt;.</Statement>
    </Statements>
    <GradeLevels>
      <GradeLevel>08</GradeLevel>
    </GradeLevels>
    <LearningStandardDocumentRefId>B62C1C106873438AA0126760075A65A3</LearningStandardDocumentRefId>
    <RelatedLearningStandardItems>
      <LearningStandardItemRefId RelationshipType="childOf">42D43D973FEF4A028D2AEAC7151A01DB</LearningStandardItemRefId>
    </RelatedLearningStandardItems>
  </LearningStandardItem>
  <LearningStandardItem xml:lang="en" RefID="E625C65889F547ED92819D3B9F7C4216">
    <RefURI>http://corestandards.org/Math/Content/8/EE/A/4/</RefURI>
    <StandardHierarchyLevel>
      <number>7</number>
      <description>Standard</description>
    </StandardHierarchyLevel>
    <StatementCodes>
      <StatementCode>CCSS.Math.Content.8.EE.A.4</StatementCode>
    </StatementCodes>
    <Statements>
      <Statement>Perform operations with numbers expressed in scientific notation, including problems where both decimal and scientific notation are used. Use scientific notation and choose units of appropriate size for measurements of very large or very small quantities (e.g., use millimeters per year for seafloor spreading). Interpret scientific notation that has been generated by technology</Statement>
    </Statements>
    <GradeLevels>
      <GradeLevel>08</GradeLevel>
    </GradeLevels>
    <LearningStandardDocumentRefId>B62C1C106873438AA0126760075A65A3</LearningStandardDocumentRefId>
    <RelatedLearningStandardItems>
      <LearningStandardItemRefId RelationshipType="childOf">42D43D973FEF4A028D2AEAC7151A01DB</LearningStandardItemRefId>
    </RelatedLearningStandardItems>
  </LearningStandardItem>
  <LearningStandardItem xml:lang="en" RefID="E2FCE06C6D0649DAB51E7FAB19A6BB8B">
    <RefURI>http://corestandards.org/Math/Content/8/EE/B/5/</RefURI>
    <StandardHierarchyLevel>
      <number>7</number>
      <description>Standard</description>
    </StandardHierarchyLevel>
    <StatementCodes>
      <StatementCode>CCSS.Math.Content.8.EE.B.5</StatementCode>
    </StatementCodes>
    <Statements>
      <Statement>Graph proportional relationships, interpreting the unit rate as the slope of the graph. Compare two different proportional relationships represented in different ways. For example, compare a distance-time graph to a distance-time equation to determine which of two moving objects has greater speed.</Statement>
    </Statements>
    <GradeLevels>
      <GradeLevel>08</GradeLevel>
    </GradeLevels>
    <LearningStandardDocumentRefId>B62C1C106873438AA0126760075A65A3</LearningStandardDocumentRefId>
    <RelatedLearningStandardItems>
      <LearningStandardItemRefId RelationshipType="childOf">D41D63A930114002AC63910B8A561DBD</LearningStandardItemRefId>
    </RelatedLearningStandardItems>
  </LearningStandardItem>
  <LearningStandardItem xml:lang="en" RefID="607B0D02788646F4895FE734C9EE481A">
    <RefURI>http://corestandards.org/Math/Content/8/EE/B/6/</RefURI>
    <StandardHierarchyLevel>
      <number>7</number>
      <description>Standard</description>
    </StandardHierarchyLevel>
    <StatementCodes>
      <StatementCode>CCSS.Math.Content.8.EE.B.6</StatementCode>
    </StatementCodes>
    <Statements>
      <Statement>Use similar triangles to explain why the slope m is the same between any two distinct points on a non-vertical line in the coordinate plane; derive the equation y = mx for a line through the origin and the equation &lt;i&gt;y&lt;/i&gt; = &lt;i&gt;mx&lt;/i&gt; + &lt;i&gt;b&lt;/i&gt; for a line intercepting the vertical axis at &lt;i&gt;b&lt;/i&gt;.</Statement>
    </Statements>
    <GradeLevels>
      <GradeLevel>08</GradeLevel>
    </GradeLevels>
    <LearningStandardDocumentRefId>B62C1C106873438AA0126760075A65A3</LearningStandardDocumentRefId>
    <RelatedLearningStandardItems>
      <LearningStandardItemRefId RelationshipType="childOf">D41D63A930114002AC63910B8A561DBD</LearningStandardItemRefId>
    </RelatedLearningStandardItems>
  </LearningStandardItem>
  <LearningStandardItem xml:lang="en" RefID="7276B02F0B004E889E6355C98B8C1F62">
    <RefURI>http://corestandards.org/Math/Content/8/EE/C/7/</RefURI>
    <StandardHierarchyLevel>
      <number>7</number>
      <description>Standard</description>
    </StandardHierarchyLevel>
    <StatementCodes>
      <StatementCode>CCSS.Math.Content.8.EE.C.7</StatementCode>
    </StatementCodes>
    <Statements>
      <Statement>Solve linear equations in one variable.</Statement>
    </Statements>
    <GradeLevels>
      <GradeLevel>08</GradeLevel>
    </GradeLevels>
    <LearningStandardDocumentRefId>B62C1C106873438AA0126760075A65A3</LearningStandardDocumentRefId>
    <RelatedLearningStandardItems>
      <LearningStandardItemRefId RelationshipType="childOf">29419E561D0F4947929F5400799CB6ED</LearningStandardItemRefId>
    </RelatedLearningStandardItems>
  </LearningStandardItem>
  <LearningStandardItem xml:lang="en" RefID="37D0AF8DE45246A1BE82DA6ACB8DC0D4">
    <RefURI>http://corestandards.org/Math/Content/8/EE/C/7/a/</RefURI>
    <StandardHierarchyLevel>
      <number>8</number>
      <description>Component</description>
    </StandardHierarchyLevel>
    <StatementCodes>
      <StatementCode>CCSS.Math.Content.8.EE.C.7a</StatementCode>
    </StatementCodes>
    <Statements>
      <Statement>Give examples of linear equations in one variable with one solution, infinitely many solutions, or no solutions. Show which of these possibilities is the case by successively transforming the given equation into simpler forms, until an equivalent equation of the form &lt;i&gt;x&lt;/i&gt; = &lt;i&gt;a&lt;/i&gt;, &lt;i&gt;a&lt;/i&gt; = &lt;i&gt;a&lt;/i&gt;, or &lt;i&gt;a&lt;/i&gt; = &lt;i&gt;b&lt;/i&gt; results (where &lt;i&gt;a&lt;/i&gt; and &lt;i&gt;b&lt;/i&gt; are different numbers).</Statement>
    </Statements>
    <GradeLevels>
      <GradeLevel>08</GradeLevel>
    </GradeLevels>
    <LearningStandardDocumentRefId>B62C1C106873438AA0126760075A65A3</LearningStandardDocumentRefId>
    <RelatedLearningStandardItems>
      <LearningStandardItemRefId RelationshipType="childOf">7276B02F0B004E889E6355C98B8C1F62</LearningStandardItemRefId>
    </RelatedLearningStandardItems>
  </LearningStandardItem>
  <LearningStandardItem xml:lang="en" RefID="DC8116E17B134614B9C311DB843BD9FA">
    <RefURI>http://corestandards.org/Math/Content/8/EE/C/7/b/</RefURI>
    <StandardHierarchyLevel>
      <number>8</number>
      <description>Component</description>
    </StandardHierarchyLevel>
    <StatementCodes>
      <StatementCode>CCSS.Math.Content.8.EE.C.7b</StatementCode>
    </StatementCodes>
    <Statements>
      <Statement>Solve linear equations with rational number coefficients, including equations whose solutions require expanding expressions using the distributive property and collecting like terms.</Statement>
    </Statements>
    <GradeLevels>
      <GradeLevel>08</GradeLevel>
    </GradeLevels>
    <LearningStandardDocumentRefId>B62C1C106873438AA0126760075A65A3</LearningStandardDocumentRefId>
    <RelatedLearningStandardItems>
      <LearningStandardItemRefId RelationshipType="childOf">7276B02F0B004E889E6355C98B8C1F62</LearningStandardItemRefId>
    </RelatedLearningStandardItems>
  </LearningStandardItem>
  <LearningStandardItem xml:lang="en" RefID="6FC2501BA58B4695979EA68AC7E2C987">
    <RefURI>http://corestandards.org/Math/Content/8/EE/C/8/</RefURI>
    <StandardHierarchyLevel>
      <number>7</number>
      <description>Standard</description>
    </StandardHierarchyLevel>
    <StatementCodes>
      <StatementCode>CCSS.Math.Content.8.EE.C.8</StatementCode>
    </StatementCodes>
    <Statements>
      <Statement>Analyze and solve pairs of simultaneous linear equations.</Statement>
    </Statements>
    <GradeLevels>
      <GradeLevel>08</GradeLevel>
    </GradeLevels>
    <LearningStandardDocumentRefId>B62C1C106873438AA0126760075A65A3</LearningStandardDocumentRefId>
    <RelatedLearningStandardItems>
      <LearningStandardItemRefId RelationshipType="childOf">29419E561D0F4947929F5400799CB6ED</LearningStandardItemRefId>
    </RelatedLearningStandardItems>
  </LearningStandardItem>
  <LearningStandardItem xml:lang="en" RefID="C8EFEC63BD1C4E8AB40AE467EF904347">
    <RefURI>http://corestandards.org/Math/Content/8/EE/C/8/a/</RefURI>
    <StandardHierarchyLevel>
      <number>8</number>
      <description>Component</description>
    </StandardHierarchyLevel>
    <StatementCodes>
      <StatementCode>CCSS.Math.Content.8.EE.C.8a</StatementCode>
    </StatementCodes>
    <Statements>
      <Statement>Understand that solutions to a system of two linear equations in two variables correspond to points of intersection of their graphs, because points of intersection satisfy both equations simultaneously.</Statement>
    </Statements>
    <GradeLevels>
      <GradeLevel>08</GradeLevel>
    </GradeLevels>
    <LearningStandardDocumentRefId>B62C1C106873438AA0126760075A65A3</LearningStandardDocumentRefId>
    <RelatedLearningStandardItems>
      <LearningStandardItemRefId RelationshipType="childOf">6FC2501BA58B4695979EA68AC7E2C987</LearningStandardItemRefId>
    </RelatedLearningStandardItems>
  </LearningStandardItem>
  <LearningStandardItem xml:lang="en" RefID="C837C873D4C94DC9BB08D7525EA73A5C">
    <RefURI>http://corestandards.org/Math/Content/8/EE/C/8/b/</RefURI>
    <StandardHierarchyLevel>
      <number>8</number>
      <description>Component</description>
    </StandardHierarchyLevel>
    <StatementCodes>
      <StatementCode>CCSS.Math.Content.8.EE.C.8b</StatementCode>
    </StatementCodes>
    <Statements>
      <Statement>Solve systems of two linear equations in two variables algebraically, and estimate solutions by graphing the equations. Solve simple cases by inspection. &lt;i&gt;For example, 3x + 2y = 5 and 3x + 2y = 6 have no solution because 3x + 2y cannot simultaneously be 5 and 6&lt;/i&gt;.</Statement>
    </Statements>
    <GradeLevels>
      <GradeLevel>08</GradeLevel>
    </GradeLevels>
    <LearningStandardDocumentRefId>B62C1C106873438AA0126760075A65A3</LearningStandardDocumentRefId>
    <RelatedLearningStandardItems>
      <LearningStandardItemRefId RelationshipType="childOf">6FC2501BA58B4695979EA68AC7E2C987</LearningStandardItemRefId>
    </RelatedLearningStandardItems>
  </LearningStandardItem>
  <LearningStandardItem xml:lang="en" RefID="6319C40BAA4B4B2F8D2B8BF2CA02D465">
    <RefURI>http://corestandards.org/Math/Content/8/EE/C/8/c/</RefURI>
    <StandardHierarchyLevel>
      <number>8</number>
      <description>Component</description>
    </StandardHierarchyLevel>
    <StatementCodes>
      <StatementCode>CCSS.Math.Content.8.EE.C.8c</StatementCode>
    </StatementCodes>
    <Statements>
      <Statement>Solve real-world and mathematical problems leading to two linear equations in two variables. &lt;i&gt;For example, given coordinates for two pairs of points, determine whether the line through the first pair of points intersects the line through the second pair&lt;/i&gt;.</Statement>
    </Statements>
    <GradeLevels>
      <GradeLevel>08</GradeLevel>
    </GradeLevels>
    <LearningStandardDocumentRefId>B62C1C106873438AA0126760075A65A3</LearningStandardDocumentRefId>
    <RelatedLearningStandardItems>
      <LearningStandardItemRefId RelationshipType="childOf">6FC2501BA58B4695979EA68AC7E2C987</LearningStandardItemRefId>
    </RelatedLearningStandardItems>
  </LearningStandardItem>
</LearningStandards>
