<?xml version="1.0" encoding="UTF-8"?>
<LearningStandards>
  <LearningStandardItem xml:lang="en" RefID="B5C30677172145f0B4FB0846A1F4E9E2">
    <RefURI>http://corestandards.org/ELA-Literacy/W/11-12/1/</RefURI>
    <StandardHierarchyLevel>
      <number>6</number>
      <description>Standard</description>
    </StandardHierarchyLevel>
    <StatementCodes>
      <StatementCode>CCSS.ELA-Literacy.W.11-12.1</StatementCode>
    </StatementCodes>
    <Statements>
      <Statement>Write arguments to support claims in an analysis of substantive topics or texts, using valid reasoning and relevant and sufficient evidence.</Statement>
    </Statements>
    <GradeLevels>
      <GradeLevel>11-12</GradeLevel>
    </GradeLevels>
    <LearningStandardDocumentRefId>0FAC40650F514a459951A657F942B845</LearningStandardDocumentRefId>
    <RelatedLearningStandardItems>
      <LearningStandardItemRefId RelationshipType="childOf">829CFFF273FE4d2794FD0ED2A7D880FC</LearningStandardItemRefId>
    </RelatedLearningStandardItems>
  </LearningStandardItem>
  <LearningStandardItem xml:lang="en" RefID="D31592D8785C41d0A679DA72B45BD1A4">
    <RefURI>http://corestandards.org/ELA-Literacy/W/11-12/1/a/</RefURI>
    <StandardHierarchyLevel>
      <number>7</number>
      <description>Component</description>
    </StandardHierarchyLevel>
    <StatementCodes>
      <StatementCode>CCSS.ELA-Literacy.W.11-12.1a</StatementCode>
    </StatementCodes>
    <Statements>
      <Statement>Introduce precise, knowledgeable claim(s), establish the significance of the claim(s), distinguish the claim(s) from alternate or opposing claims, and create an organization that logically sequences claim(s), counterclaims, reasons, and evidence.</Statement>
    </Statements>
    <GradeLevels>
      <GradeLevel>11-12</GradeLevel>
    </GradeLevels>
    <LearningStandardDocumentRefId>0FAC40650F514a459951A657F942B845</LearningStandardDocumentRefId>
    <RelatedLearningStandardItems>
      <LearningStandardItemRefId RelationshipType="childOf">B5C30677172145f0B4FB0846A1F4E9E2</LearningStandardItemRefId>
    </RelatedLearningStandardItems>
  </LearningStandardItem>
  <LearningStandardItem xml:lang="en" RefID="BDD7851907FA438dA0F7DFD17971FA88">
    <RefURI>http://corestandards.org/ELA-Literacy/W/11-12/1/b/</RefURI>
    <StandardHierarchyLevel>
      <number>7</number>
      <description>Component</description>
    </StandardHierarchyLevel>
    <StatementCodes>
      <StatementCode>CCSS.ELA-Literacy.W.11-12.1b</StatementCode>
    </StatementCodes>
    <Statements>
      <Statement>Develop claim(s) and counterclaims fairly and thoroughly, supplying the most relevant evidence for each while pointing out the strengths and limitations of both in a manner that anticipates the audience&amp;rsquo;s knowledge level, concerns, values, and possible biases.</Statement>
    </Statements>
    <GradeLevels>
      <GradeLevel>11-12</GradeLevel>
    </GradeLevels>
    <LearningStandardDocumentRefId>0FAC40650F514a459951A657F942B845</LearningStandardDocumentRefId>
    <RelatedLearningStandardItems>
      <LearningStandardItemRefId RelationshipType="childOf">B5C30677172145f0B4FB0846A1F4E9E2</LearningStandardItemRefId>
    </RelatedLearningStandardItems>
  </LearningStandardItem>
  <LearningStandardItem xml:lang="en" RefID="45F3D3D6ABCA4f2684ADDD19DF99D128">
    <RefURI>http://corestandards.org/ELA-Literacy/W/11-12/1/c/</RefURI>
    <StandardHierarchyLevel>
      <number>7</number>
      <description>Component</description>
    </StandardHierarchyLevel>
    <StatementCodes>
      <StatementCode>CCSS.ELA-Literacy.W.11-12.1c</StatementCode>
    </StatementCodes>
    <Statements>
      <Statement>Use words, phrases, and clauses as well as varied syntax to link the major sections of the text, create cohesion, and clarify the relationships between claim(s) and reasons, between reasons and evidence, and between claim(s) and counterclaims.</Statement>
    </Statements>
    <GradeLevels>
      <GradeLevel>11-12</GradeLevel>
    </GradeLevels>
    <LearningStandardDocumentRefId>0FAC40650F514a459951A657F942B845</LearningStandardDocumentRefId>
    <RelatedLearningStandardItems>
      <LearningStandardItemRefId RelationshipType="childOf">B5C30677172145f0B4FB0846A1F4E9E2</LearningStandardItemRefId>
    </RelatedLearningStandardItems>
  </LearningStandardItem>
  <LearningStandardItem xml:lang="en" RefID="34961DF0D6BE4df1AB851489BB1A1CB4">
    <RefURI>http://corestandards.org/ELA-Literacy/W/11-12/1/d/</RefURI>
    <StandardHierarchyLevel>
      <number>7</number>
      <description>Component</description>
    </StandardHierarchyLevel>
    <StatementCodes>
      <StatementCode>CCSS.ELA-Literacy.W.11-12.1d</StatementCode>
    </StatementCodes>
    <Statements>
      <Statement>Establish and maintain a formal style and objective tone while attending to the norms and conventions of the discipline in which they are writing.</Statement>
    </Statements>
    <GradeLevels>
      <GradeLevel>11-12</GradeLevel>
    </GradeLevels>
    <LearningStandardDocumentRefId>0FAC40650F514a459951A657F942B845</LearningStandardDocumentRefId>
    <RelatedLearningStandardItems>
      <LearningStandardItemRefId RelationshipType="childOf">B5C30677172145f0B4FB0846A1F4E9E2</LearningStandardItemRefId>
    </RelatedLearningStandardItems>
  </LearningStandardItem>
  <LearningStandardItem xml:lang="en" RefID="81FAA33B5FA3496d85048A8406664504">
    <RefURI>http://corestandards.org/ELA-Literacy/W/11-12/1/e/</RefURI>
    <StandardHierarchyLevel>
      <number>7</number>
      <description>Component</description>
    </StandardHierarchyLevel>
    <StatementCodes>
      <StatementCode>CCSS.ELA-Literacy.W.11-12.1e</StatementCode>
    </StatementCodes>
    <Statements>
      <Statement>Provide a concluding statement or section that follows from and supports the argument presented.</Statement>
    </Statements>
    <GradeLevels>
      <GradeLevel>11-12</GradeLevel>
    </GradeLevels>
    <LearningStandardDocumentRefId>0FAC40650F514a459951A657F942B845</LearningStandardDocumentRefId>
    <RelatedLearningStandardItems>
      <LearningStandardItemRefId RelationshipType="childOf">B5C30677172145f0B4FB0846A1F4E9E2</LearningStandardItemRefId>
    </RelatedLearningStandardItems>
  </LearningStandardItem>
  <LearningStandardItem xml:lang="en" RefID="713DB49BCDF74b8fA3F8973D0BF25929">
    <RefURI>http://corestandards.org/ELA-Literacy/W/11-12/2/</RefURI>
    <StandardHierarchyLevel>
      <number>6</number>
      <description>Standard</description>
    </StandardHierarchyLevel>
    <StatementCodes>
      <StatementCode>CCSS.ELA-Literacy.W.11-12.2</StatementCode>
    </StatementCodes>
    <Statements>
      <Statement>Write informative/explanatory texts to examine and convey complex ideas, concepts, and information clearly and accurately through the effective selection, organization, and analysis of content.</Statement>
    </Statements>
    <GradeLevels>
      <GradeLevel>11-12</GradeLevel>
    </GradeLevels>
    <LearningStandardDocumentRefId>0FAC40650F514a459951A657F942B845</LearningStandardDocumentRefId>
    <RelatedLearningStandardItems>
      <LearningStandardItemRefId RelationshipType="childOf">829CFFF273FE4d2794FD0ED2A7D880FC</LearningStandardItemRefId>
    </RelatedLearningStandardItems>
  </LearningStandardItem>
  <LearningStandardItem xml:lang="en" RefID="55ADA701DF7840ed97DB01863150ABDA">
    <RefURI>http://corestandards.org/ELA-Literacy/W/11-12/2/a/</RefURI>
    <StandardHierarchyLevel>
      <number>7</number>
      <description>Component</description>
    </StandardHierarchyLevel>
    <StatementCodes>
      <StatementCode>CCSS.ELA-Literacy.W.11-12.2a</StatementCode>
    </StatementCodes>
    <Statements>
      <Statement>Introduce a topic; organize complex ideas, concepts, and information so that each new element builds on that which precedes it to create a unified whole; include formatting (e.g., headings), graphics (e.g., figures, tables), and multimedia when useful to aiding comprehension.</Statement>
    </Statements>
    <GradeLevels>
      <GradeLevel>11-12</GradeLevel>
    </GradeLevels>
    <LearningStandardDocumentRefId>0FAC40650F514a459951A657F942B845</LearningStandardDocumentRefId>
    <RelatedLearningStandardItems>
      <LearningStandardItemRefId RelationshipType="childOf">713DB49BCDF74b8fA3F8973D0BF25929</LearningStandardItemRefId>
    </RelatedLearningStandardItems>
  </LearningStandardItem>
  <LearningStandardItem xml:lang="en" RefID="C439F7D3ABBE44b8A7D69A6C1B420177">
    <RefURI>http://corestandards.org/ELA-Literacy/W/11-12/2/b/</RefURI>
    <StandardHierarchyLevel>
      <number>7</number>
      <description>Component</description>
    </StandardHierarchyLevel>
    <StatementCodes>
      <StatementCode>CCSS.ELA-Literacy.W.11-12.2b</StatementCode>
    </StatementCodes>
    <Statements>
      <Statement>Develop the topic thoroughly by selecting the most significant and relevant facts, extended definitions, concrete details, quotations, or other information and examples appropriate to the audience&amp;rsquo;s knowledge of the topic.</Statement>
    </Statements>
    <GradeLevels>
      <GradeLevel>11-12</GradeLevel>
    </GradeLevels>
    <LearningStandardDocumentRefId>0FAC40650F514a459951A657F942B845</LearningStandardDocumentRefId>
    <RelatedLearningStandardItems>
      <LearningStandardItemRefId RelationshipType="childOf">713DB49BCDF74b8fA3F8973D0BF25929</LearningStandardItemRefId>
    </RelatedLearningStandardItems>
  </LearningStandardItem>
  <LearningStandardItem xml:lang="en" RefID="29059D99E58347a6B8A128FF1FB089DA">
    <RefURI>http://corestandards.org/ELA-Literacy/W/11-12/2/c/</RefURI>
    <StandardHierarchyLevel>
      <number>7</number>
      <description>Component</description>
    </StandardHierarchyLevel>
    <StatementCodes>
      <StatementCode>CCSS.ELA-Literacy.W.11-12.2c</StatementCode>
    </StatementCodes>
    <Statements>
      <Statement>Use appropriate and varied transitions and syntax to link the major sections of the text, create cohesion, and clarify the relationships among complex ideas and concepts.</Statement>
    </Statements>
    <GradeLevels>
      <GradeLevel>11-12</GradeLevel>
    </GradeLevels>
    <LearningStandardDocumentRefId>0FAC40650F514a459951A657F942B845</LearningStandardDocumentRefId>
    <RelatedLearningStandardItems>
      <LearningStandardItemRefId RelationshipType="childOf">713DB49BCDF74b8fA3F8973D0BF25929</LearningStandardItemRefId>
    </RelatedLearningStandardItems>
  </LearningStandardItem>
  <LearningStandardItem xml:lang="en" RefID="9D6E0F3703E14c65ABDF78AC8F4DC055">
    <RefURI>http://corestandards.org/ELA-Literacy/W/11-12/2/d/</RefURI>
    <StandardHierarchyLevel>
      <number>7</number>
      <description>Component</description>
    </StandardHierarchyLevel>
    <StatementCodes>
      <StatementCode>CCSS.ELA-Literacy.W.11-12.2d</StatementCode>
    </StatementCodes>
    <Statements>
      <Statement>Use precise language, domain-specific vocabulary, and techniques such as metaphor, simile, and analogy to manage the complexity of the topic.</Statement>
    </Statements>
    <GradeLevels>
      <GradeLevel>11-12</GradeLevel>
    </GradeLevels>
    <LearningStandardDocumentRefId>0FAC40650F514a459951A657F942B845</LearningStandardDocumentRefId>
    <RelatedLearningStandardItems>
      <LearningStandardItemRefId RelationshipType="childOf">713DB49BCDF74b8fA3F8973D0BF25929</LearningStandardItemRefId>
    </RelatedLearningStandardItems>
  </LearningStandardItem>
  <LearningStandardItem xml:lang="en" RefID="09A448877DC3442e892F7470058649A5">
    <RefURI>http://corestandards.org/ELA-Literacy/W/11-12/2/e/</RefURI>
    <StandardHierarchyLevel>
      <number>7</number>
      <description>Component</description>
    </StandardHierarchyLevel>
    <StatementCodes>
      <StatementCode>CCSS.ELA-Literacy.W.11-12.2e</StatementCode>
    </StatementCodes>
    <Statements>
      <Statement>Establish and maintain a formal style and objective tone while attending to the norms and conventions of the discipline in which they are writing.</Statement>
    </Statements>
    <GradeLevels>
      <GradeLevel>11-12</GradeLevel>
    </GradeLevels>
    <LearningStandardDocumentRefId>0FAC40650F514a459951A657F942B845</LearningStandardDocumentRefId>
    <RelatedLearningStandardItems>
      <LearningStandardItemRefId RelationshipType="childOf">713DB49BCDF74b8fA3F8973D0BF25929</LearningStandardItemRefId>
    </RelatedLearningStandardItems>
  </LearningStandardItem>
  <LearningStandardItem xml:lang="en" RefID="8CA33B61DD6546778B0035A298026A1D">
    <RefURI>http://corestandards.org/ELA-Literacy/W/11-12/2/f/</RefURI>
    <StandardHierarchyLevel>
      <number>7</number>
      <description>Component</description>
    </StandardHierarchyLevel>
    <StatementCodes>
      <StatementCode>CCSS.ELA-Literacy.W.11-12.2f</StatementCode>
    </StatementCodes>
    <Statements>
      <Statement>Provide a concluding statement or section that follows from and supports the information or explanation presented (e.g., articulating implications or the significance of the topic).</Statement>
    </Statements>
    <GradeLevels>
      <GradeLevel>11-12</GradeLevel>
    </GradeLevels>
    <LearningStandardDocumentRefId>0FAC40650F514a459951A657F942B845</LearningStandardDocumentRefId>
    <RelatedLearningStandardItems>
      <LearningStandardItemRefId RelationshipType="childOf">713DB49BCDF74b8fA3F8973D0BF25929</LearningStandardItemRefId>
    </RelatedLearningStandardItems>
  </LearningStandardItem>
  <LearningStandardItem xml:lang="en" RefID="8DAAA417A7FE4c7a8092BA3EEDD0859A">
    <RefURI>http://corestandards.org/ELA-Literacy/W/11-12/3/</RefURI>
    <StandardHierarchyLevel>
      <number>6</number>
      <description>Standard</description>
    </StandardHierarchyLevel>
    <StatementCodes>
      <StatementCode>CCSS.ELA-Literacy.W.11-12.3</StatementCode>
    </StatementCodes>
    <Statements>
      <Statement>Write narratives to develop real or imagined experiences or events using effective technique, well-chosen details, and well-structured event sequences.</Statement>
    </Statements>
    <GradeLevels>
      <GradeLevel>11-12</GradeLevel>
    </GradeLevels>
    <LearningStandardDocumentRefId>0FAC40650F514a459951A657F942B845</LearningStandardDocumentRefId>
    <RelatedLearningStandardItems>
      <LearningStandardItemRefId RelationshipType="childOf">829CFFF273FE4d2794FD0ED2A7D880FC</LearningStandardItemRefId>
    </RelatedLearningStandardItems>
  </LearningStandardItem>
  <LearningStandardItem xml:lang="en" RefID="B4A824ED0CB6405bB9858FD557867737">
    <RefURI>http://corestandards.org/ELA-Literacy/W/11-12/3/a/</RefURI>
    <StandardHierarchyLevel>
      <number>7</number>
      <description>Component</description>
    </StandardHierarchyLevel>
    <StatementCodes>
      <StatementCode>CCSS.ELA-Literacy.W.11-12.3a</StatementCode>
    </StatementCodes>
    <Statements>
      <Statement>Engage and orient the reader by setting out a problem, situation, or observation and its significance, establishing one or multiple point(s) of view, and introducing a narrator and/or characters; create a smooth progression of experiences or events.</Statement>
    </Statements>
    <GradeLevels>
      <GradeLevel>11-12</GradeLevel>
    </GradeLevels>
    <LearningStandardDocumentRefId>0FAC40650F514a459951A657F942B845</LearningStandardDocumentRefId>
    <RelatedLearningStandardItems>
      <LearningStandardItemRefId RelationshipType="childOf">8DAAA417A7FE4c7a8092BA3EEDD0859A</LearningStandardItemRefId>
    </RelatedLearningStandardItems>
  </LearningStandardItem>
  <LearningStandardItem xml:lang="en" RefID="D9397AB8211F42258FA5235D168F19DE">
    <RefURI>http://corestandards.org/ELA-Literacy/W/11-12/3/b/</RefURI>
    <StandardHierarchyLevel>
      <number>7</number>
      <description>Component</description>
    </StandardHierarchyLevel>
    <StatementCodes>
      <StatementCode>CCSS.ELA-Literacy.W.11-12.3b</StatementCode>
    </StatementCodes>
    <Statements>
      <Statement>Use narrative techniques, such as dialogue, pacing, description, reflection, and multiple plot lines, to develop experiences, events, and/or characters.</Statement>
    </Statements>
    <GradeLevels>
      <GradeLevel>11-12</GradeLevel>
    </GradeLevels>
    <LearningStandardDocumentRefId>0FAC40650F514a459951A657F942B845</LearningStandardDocumentRefId>
    <RelatedLearningStandardItems>
      <LearningStandardItemRefId RelationshipType="childOf">8DAAA417A7FE4c7a8092BA3EEDD0859A</LearningStandardItemRefId>
    </RelatedLearningStandardItems>
  </LearningStandardItem>
  <LearningStandardItem xml:lang="en" RefID="0F4129AFE5B545dfB462682EE6817BB1">
    <RefURI>http://corestandards.org/ELA-Literacy/W/11-12/3/c/</RefURI>
    <StandardHierarchyLevel>
      <number>7</number>
      <description>Component</description>
    </StandardHierarchyLevel>
    <StatementCodes>
      <StatementCode>CCSS.ELA-Literacy.W.11-12.3c</StatementCode>
    </StatementCodes>
    <Statements>
      <Statement>Use a variety of techniques to sequence events so that they build on one another to create a coherent whole and build toward a particular tone and outcome (e.g., a sense of mystery, suspense, growth, or resolution).</Statement>
    </Statements>
    <GradeLevels>
      <GradeLevel>11-12</GradeLevel>
    </GradeLevels>
    <LearningStandardDocumentRefId>0FAC40650F514a459951A657F942B845</LearningStandardDocumentRefId>
    <RelatedLearningStandardItems>
      <LearningStandardItemRefId RelationshipType="childOf">8DAAA417A7FE4c7a8092BA3EEDD0859A</LearningStandardItemRefId>
    </RelatedLearningStandardItems>
  </LearningStandardItem>
  <LearningStandardItem xml:lang="en" RefID="C287BC5B13144a3c9CC4E15737E5B4B4">
    <RefURI>http://corestandards.org/ELA-Literacy/W/11-12/3/d/</RefURI>
    <StandardHierarchyLevel>
      <number>7</number>
      <description>Component</description>
    </StandardHierarchyLevel>
    <StatementCodes>
      <StatementCode>CCSS.ELA-Literacy.W.11-12.3d</StatementCode>
    </StatementCodes>
    <Statements>
      <Statement>Use precise words and phrases, telling details, and sensory language to convey a vivid picture of the experiences, events, setting, and/or characters.</Statement>
    </Statements>
    <GradeLevels>
      <GradeLevel>11-12</GradeLevel>
    </GradeLevels>
    <LearningStandardDocumentRefId>0FAC40650F514a459951A657F942B845</LearningStandardDocumentRefId>
    <RelatedLearningStandardItems>
      <LearningStandardItemRefId RelationshipType="childOf">8DAAA417A7FE4c7a8092BA3EEDD0859A</LearningStandardItemRefId>
    </RelatedLearningStandardItems>
  </LearningStandardItem>
  <LearningStandardItem xml:lang="en" RefID="8C084761897F464e95D9D6B2823DF471">
    <RefURI>http://corestandards.org/ELA-Literacy/W/11-12/3/e/</RefURI>
    <StandardHierarchyLevel>
      <number>7</number>
      <description>Component</description>
    </StandardHierarchyLevel>
    <StatementCodes>
      <StatementCode>CCSS.ELA-Literacy.W.11-12.3e</StatementCode>
    </StatementCodes>
    <Statements>
      <Statement>Provide a conclusion that follows from and reflects on what is experienced, observed, or resolved over the course of the narrative.</Statement>
    </Statements>
    <GradeLevels>
      <GradeLevel>11-12</GradeLevel>
    </GradeLevels>
    <LearningStandardDocumentRefId>0FAC40650F514a459951A657F942B845</LearningStandardDocumentRefId>
    <RelatedLearningStandardItems>
      <LearningStandardItemRefId RelationshipType="childOf">8DAAA417A7FE4c7a8092BA3EEDD0859A</LearningStandardItemRefId>
    </RelatedLearningStandardItems>
  </LearningStandardItem>
  <LearningStandardItem xml:lang="en" RefID="E5DE9EBD57154eb5898E523B38BC431A">
    <RefURI>http://corestandards.org/ELA-Literacy/W/11-12/4/</RefURI>
    <StandardHierarchyLevel>
      <number>6</number>
      <description>Standard</description>
    </StandardHierarchyLevel>
    <StatementCodes>
      <StatementCode>CCSS.ELA-Literacy.W.11-12.4</StatementCode>
    </StatementCodes>
    <Statements>
      <Statement>Produce clear and coherent writing in which the development, organization, and style are appropriate to task, purpose, and audience. (Grade-specific expectations for writing types are defined in standards 1&amp;ndash;3 above.)</Statement>
    </Statements>
    <GradeLevels>
      <GradeLevel>11-12</GradeLevel>
    </GradeLevels>
    <LearningStandardDocumentRefId>0FAC40650F514a459951A657F942B845</LearningStandardDocumentRefId>
    <RelatedLearningStandardItems>
      <LearningStandardItemRefId RelationshipType="childOf">829CFFF273FE4d2794FD0ED2A7D880FC</LearningStandardItemRefId>
    </RelatedLearningStandardItems>
  </LearningStandardItem>
  <LearningStandardItem xml:lang="en" RefID="40E2C27A62A34ee08B5057279E5FD92F">
    <RefURI>http://corestandards.org/ELA-Literacy/W/11-12/5/</RefURI>
    <StandardHierarchyLevel>
      <number>6</number>
      <description>Standard</description>
    </StandardHierarchyLevel>
    <StatementCodes>
      <StatementCode>CCSS.ELA-Literacy.W.11-12.5</StatementCode>
    </StatementCodes>
    <Statements>
      <Statement>Develop and strengthen writing as needed by planning, revising, editing, rewriting, or trying a new approach, focusing on addressing what is most significant for a specific purpose and audience. (Editing for conventions should demonstrate command of Language standards 1&#8211;3 up to and including grades 11&#8211;12 &lt;a href=&quot;/ELA-Literacy/L/11-12&quot;&gt;here&lt;/a&gt;.)</Statement>
    </Statements>
    <GradeLevels>
      <GradeLevel>11-12</GradeLevel>
    </GradeLevels>
    <LearningStandardDocumentRefId>0FAC40650F514a459951A657F942B845</LearningStandardDocumentRefId>
    <RelatedLearningStandardItems>
      <LearningStandardItemRefId RelationshipType="childOf">829CFFF273FE4d2794FD0ED2A7D880FC</LearningStandardItemRefId>
    </RelatedLearningStandardItems>
  </LearningStandardItem>
  <LearningStandardItem xml:lang="en" RefID="160D84A8AB6E4d46BBA19526D5343495">
    <RefURI>http://corestandards.org/ELA-Literacy/W/11-12/6/</RefURI>
    <StandardHierarchyLevel>
      <number>6</number>
      <description>Standard</description>
    </StandardHierarchyLevel>
    <StatementCodes>
      <StatementCode>CCSS.ELA-Literacy.W.11-12.6</StatementCode>
    </StatementCodes>
    <Statements>
      <Statement>Use technology, including the Internet, to produce, publish, and update individual or shared writing products in response to ongoing feedback, including new arguments or information.</Statement>
    </Statements>
    <GradeLevels>
      <GradeLevel>11-12</GradeLevel>
    </GradeLevels>
    <LearningStandardDocumentRefId>0FAC40650F514a459951A657F942B845</LearningStandardDocumentRefId>
    <RelatedLearningStandardItems>
      <LearningStandardItemRefId RelationshipType="childOf">829CFFF273FE4d2794FD0ED2A7D880FC</LearningStandardItemRefId>
    </RelatedLearningStandardItems>
  </LearningStandardItem>
  <LearningStandardItem xml:lang="en" RefID="DF04C95B69CA4514A07B9E66C441EEDF">
    <RefURI>http://corestandards.org/ELA-Literacy/W/11-12/7/</RefURI>
    <StandardHierarchyLevel>
      <number>6</number>
      <description>Standard</description>
    </StandardHierarchyLevel>
    <StatementCodes>
      <StatementCode>CCSS.ELA-Literacy.W.11-12.7</StatementCode>
    </StatementCodes>
    <Statements>
      <Statement>Conduct short as well as more sustained research projects to answer a question (including a self-generated question) or solve a problem; narrow or broaden the inquiry when appropriate; synthesize multiple sources on the subject, demonstrating understanding of the subject under investigation.</Statement>
    </Statements>
    <GradeLevels>
      <GradeLevel>11-12</GradeLevel>
    </GradeLevels>
    <LearningStandardDocumentRefId>0FAC40650F514a459951A657F942B845</LearningStandardDocumentRefId>
    <RelatedLearningStandardItems>
      <LearningStandardItemRefId RelationshipType="childOf">829CFFF273FE4d2794FD0ED2A7D880FC</LearningStandardItemRefId>
    </RelatedLearningStandardItems>
  </LearningStandardItem>
  <LearningStandardItem xml:lang="en" RefID="7C0364919CE547269C165C8A3988D8A6">
    <RefURI>http://corestandards.org/ELA-Literacy/W/11-12/8/</RefURI>
    <StandardHierarchyLevel>
      <number>6</number>
      <description>Standard</description>
    </StandardHierarchyLevel>
    <StatementCodes>
      <StatementCode>CCSS.ELA-Literacy.W.11-12.8</StatementCode>
    </StatementCodes>
    <Statements>
      <Statement>Gather relevant information from multiple authoritative print and digital sources, using advanced searches effectively; assess the strengths and limitations of each source in terms of the task, purpose, and audience; integrate information into the text selectively to maintain the flow of ideas, avoiding plagiarism and overreliance on any one source and following a standard format for citation.</Statement>
    </Statements>
    <GradeLevels>
      <GradeLevel>11-12</GradeLevel>
    </GradeLevels>
    <LearningStandardDocumentRefId>0FAC40650F514a459951A657F942B845</LearningStandardDocumentRefId>
    <RelatedLearningStandardItems>
      <LearningStandardItemRefId RelationshipType="childOf">829CFFF273FE4d2794FD0ED2A7D880FC</LearningStandardItemRefId>
    </RelatedLearningStandardItems>
  </LearningStandardItem>
  <LearningStandardItem xml:lang="en" RefID="7AC7FCDF559E470d8F436290F0785A50">
    <RefURI>http://corestandards.org/ELA-Literacy/W/11-12/9/</RefURI>
    <StandardHierarchyLevel>
      <number>6</number>
      <description>Standard</description>
    </StandardHierarchyLevel>
    <StatementCodes>
      <StatementCode>CCSS.ELA-Literacy.W.11-12.9</StatementCode>
    </StatementCodes>
    <Statements>
      <Statement>Draw evidence from literary or informational texts to support analysis, reflection, and research.</Statement>
    </Statements>
    <GradeLevels>
      <GradeLevel>11-12</GradeLevel>
    </GradeLevels>
    <LearningStandardDocumentRefId>0FAC40650F514a459951A657F942B845</LearningStandardDocumentRefId>
    <RelatedLearningStandardItems>
      <LearningStandardItemRefId RelationshipType="childOf">829CFFF273FE4d2794FD0ED2A7D880FC</LearningStandardItemRefId>
    </RelatedLearningStandardItems>
  </LearningStandardItem>
  <LearningStandardItem xml:lang="en" RefID="B6FCA3A7E8D04107B7BCEB894DFB95E2">
    <RefURI>http://corestandards.org/ELA-Literacy/W/11-12/9/a/</RefURI>
    <StandardHierarchyLevel>
      <number>7</number>
      <description>Component</description>
    </StandardHierarchyLevel>
    <StatementCodes>
      <StatementCode>CCSS.ELA-Literacy.W.11-12.9a</StatementCode>
    </StatementCodes>
    <Statements>
      <Statement>Apply g&lt;i&gt;rades 11&amp;ndash;12 Reading standards&lt;/i&gt; to literature (e.g., &amp;ldquo;Demonstrate knowledge of eighteenth-, nineteenth- and early-twentieth-century foundational works of American literature, including how two or more texts from the same period treat similar themes or topics&amp;rdquo;).</Statement>
    </Statements>
    <GradeLevels>
      <GradeLevel>11-12</GradeLevel>
    </GradeLevels>
    <LearningStandardDocumentRefId>0FAC40650F514a459951A657F942B845</LearningStandardDocumentRefId>
    <RelatedLearningStandardItems>
      <LearningStandardItemRefId RelationshipType="childOf">7AC7FCDF559E470d8F436290F0785A50</LearningStandardItemRefId>
    </RelatedLearningStandardItems>
  </LearningStandardItem>
  <LearningStandardItem xml:lang="en" RefID="A0F0184D50CC43d783C46F47816AB927">
    <RefURI>http://corestandards.org/ELA-Literacy/W/11-12/9/b/</RefURI>
    <StandardHierarchyLevel>
      <number>7</number>
      <description>Component</description>
    </StandardHierarchyLevel>
    <StatementCodes>
      <StatementCode>CCSS.ELA-Literacy.W.11-12.9b</StatementCode>
    </StatementCodes>
    <Statements>
      <Statement>Apply &lt;i&gt;grades 11&amp;ndash;12 Reading standards&lt;/i&gt; to literary nonfiction (e.g., &amp;ldquo;Delineate and evaluate the reasoning in seminal U.S. texts, including the application of constitutional principles and use of legal reasoning [e.g., in U.S. Supreme Court Case majority opinions and dissents] and the premises, purposes, and arguments in works of public advocacy [e.g., &lt;em&gt;The Federalist&lt;/em&gt;, presidential addresses]&amp;rdquo;).</Statement>
    </Statements>
    <GradeLevels>
      <GradeLevel>11-12</GradeLevel>
    </GradeLevels>
    <LearningStandardDocumentRefId>0FAC40650F514a459951A657F942B845</LearningStandardDocumentRefId>
    <RelatedLearningStandardItems>
      <LearningStandardItemRefId RelationshipType="childOf">7AC7FCDF559E470d8F436290F0785A50</LearningStandardItemRefId>
    </RelatedLearningStandardItems>
  </LearningStandardItem>
  <LearningStandardItem xml:lang="en" RefID="15048BB6CC7643d481BCD32BB751A1E1">
    <RefURI>http://corestandards.org/ELA-Literacy/W/11-12/10/</RefURI>
    <StandardHierarchyLevel>
      <number>6</number>
      <description>Standard</description>
    </StandardHierarchyLevel>
    <StatementCodes>
      <StatementCode>CCSS.ELA-Literacy.W.11-12.10</StatementCode>
    </StatementCodes>
    <Statements>
      <Statement>Write routinely over extended time frames (time for research, reflection, and revision) and shorter time frames (a single sitting or a day or two) for a range of tasks, purposes, and audiences.</Statement>
    </Statements>
    <GradeLevels>
      <GradeLevel>11-12</GradeLevel>
    </GradeLevels>
    <LearningStandardDocumentRefId>0FAC40650F514a459951A657F942B845</LearningStandardDocumentRefId>
    <RelatedLearningStandardItems>
      <LearningStandardItemRefId RelationshipType="childOf">829CFFF273FE4d2794FD0ED2A7D880FC</LearningStandardItemRefId>
    </RelatedLearningStandardItems>
  </LearningStandardItem>
</LearningStandards>
