<?xml version="1.0" encoding="UTF-8"?>
<LearningStandards>
  <LearningStandardItem xml:lang="en" RefID="5C63D948361B4814BFF237D6F97ED6E1">
    <RefURI>http://corestandards.org/Math/Content/4/MD/A/2/</RefURI>
    <StandardHierarchyLevel>
      <number>7</number>
      <description>Standard</description>
    </StandardHierarchyLevel>
    <StatementCodes>
      <StatementCode>CCSS.Math.Content.4.MD.A.2</StatementCode>
    </StatementCodes>
    <Statements>
      <Statement>Use the four operations to solve word problems involving distances, intervals of time, liquid volumes, masses of objects, and money, including problems involving simple fractions or decimals, and problems that require expressing measurements given in a larger unit in terms of a smaller unit. Represent measurement quantities using diagrams such as number line diagrams that feature a measurement scale.</Statement>
    </Statements>
    <GradeLevels>
      <GradeLevel>04</GradeLevel>
    </GradeLevels>
    <LearningStandardDocumentRefId>B62C1C106873438AA0126760075A65A3</LearningStandardDocumentRefId>
    <RelatedLearningStandardItems>
      <LearningStandardItemRefId RelationshipType="childOf">618C4BCCE83C4945B4B5F627C87798FE</LearningStandardItemRefId>
    </RelatedLearningStandardItems>
  </LearningStandardItem>
</LearningStandards>
