<?xml version="1.0" encoding="UTF-8"?>
<LearningStandards>
  <LearningStandardItem xml:lang="en" RefID="14169C01CC7844AFB61AE4FE479508A2">
    <RefURI>http://corestandards.org/Math/Content/8/SP/A/4/</RefURI>
    <StandardHierarchyLevel>
      <number>7</number>
      <description>Standard</description>
    </StandardHierarchyLevel>
    <StatementCodes>
      <StatementCode>CCSS.Math.Content.8.SP.A.4</StatementCode>
    </StatementCodes>
    <Statements>
      <Statement>Understand that patterns of association can also be seen in bivariate categorical data by displaying frequencies and relative frequencies in a two-way table. Construct and interpret a two-way table summarizing data on two categorical variables collected from the same subjects. Use relative frequencies calculated for rows or columns to describe possible association between the two variables. &lt;i&gt;For example, collect data from students in your class on whether or not they have a curfew on school nights and whether or not they have assigned chores at home. Is there evidence that those who have a curfew also tend to have chores?&lt;/i&gt;</Statement>
    </Statements>
    <GradeLevels>
      <GradeLevel>08</GradeLevel>
    </GradeLevels>
    <LearningStandardDocumentRefId>B62C1C106873438AA0126760075A65A3</LearningStandardDocumentRefId>
    <RelatedLearningStandardItems>
      <LearningStandardItemRefId RelationshipType="childOf">55CAA84D9CDF446093D0196E65CCE796</LearningStandardItemRefId>
    </RelatedLearningStandardItems>
  </LearningStandardItem>
</LearningStandards>
