<?xml version="1.0" encoding="UTF-8"?>
<LearningStandards>
  <LearningStandardItem xml:lang="en" RefID="4D8482255802431492B2AB084EA082F0">
    <RefURI>http://corestandards.org/Math/Content/5/NF/B/7/a/</RefURI>
    <StandardHierarchyLevel>
      <number>8</number>
      <description>Component</description>
    </StandardHierarchyLevel>
    <StatementCodes>
      <StatementCode>CCSS.Math.Content.5.NF.B.7a</StatementCode>
    </StatementCodes>
    <Statements>
      <Statement>Interpret division of a unit fraction by a non-zero whole number, and compute such quotients. &lt;i&gt;For example, create a story context for (1/3) &amp;divide; 4, and use a visual fraction model to show the quotient. Use the relationship between multiplication and division to explain that (1/3) &amp;divide; 4 = 1/12 because (1/12) &amp;times; 4 = 1/3&lt;/i&gt;.</Statement>
    </Statements>
    <GradeLevels>
      <GradeLevel>05</GradeLevel>
    </GradeLevels>
    <LearningStandardDocumentRefId>B62C1C106873438AA0126760075A65A3</LearningStandardDocumentRefId>
    <RelatedLearningStandardItems>
      <LearningStandardItemRefId RelationshipType="childOf">6662A64E904C4480B0940FA7F7EAE5BC</LearningStandardItemRefId>
    </RelatedLearningStandardItems>
  </LearningStandardItem>
</LearningStandards>
