<?xml version="1.0" encoding="UTF-8"?>
<LearningStandards>
  <LearningStandardItem xml:lang="en" RefID="91BEB866FC984a2bA14DAECE3B081A06">
    <RefURI>http://corestandards.org/ELA-Literacy/RI/9-10/4/</RefURI>
    <StandardHierarchyLevel>
      <number>6</number>
      <description>Standard</description>
    </StandardHierarchyLevel>
    <StatementCodes>
      <StatementCode>CCSS.ELA-Literacy.RI.9-10.4</StatementCode>
    </StatementCodes>
    <Statements>
      <Statement>Determine the meaning of words and phrases as they are used in a text, including figurative, connotative, and technical meanings; analyze the cumulative impact of specific word choices on meaning and tone (e.g., how the language of a court opinion differs from that of a newspaper).</Statement>
    </Statements>
    <GradeLevels>
      <GradeLevel>09</GradeLevel>
      <GradeLevel>10</GradeLevel>
    </GradeLevels>
    <LearningStandardDocumentRefId>0FAC40650F514a459951A657F942B845</LearningStandardDocumentRefId>
    <RelatedLearningStandardItems>
      <LearningStandardItemRefId RelationshipType="childOf">0DA1E66B47654e739180CFE53E341C4D</LearningStandardItemRefId>
    </RelatedLearningStandardItems>
  </LearningStandardItem>
</LearningStandards>
