<?xml version="1.0" encoding="UTF-8"?>
<LearningStandards>
  <LearningStandardItem xml:lang="en" RefID="161DCFEBB47B4046A4E8F7B551FD0B41">
    <RefURI>http://corestandards.org/ELA-Literacy/SL/11-12/1/</RefURI>
    <StandardHierarchyLevel>
      <number>6</number>
      <description>Standard</description>
    </StandardHierarchyLevel>
    <StatementCodes>
      <StatementCode>CCSS.ELA-Literacy.SL.11-12.1</StatementCode>
    </StatementCodes>
    <Statements>
      <Statement>Initiate and participate effectively in a range of collaborative discussions (one-on-one, in groups, and teacher-led) with diverse partners on grades 11&#8211;12 topics, texts, and issues, building on others&#8217; ideas and expressing their own clearly and persuasively.</Statement>
    </Statements>
    <GradeLevels>
      <GradeLevel>11-12</GradeLevel>
    </GradeLevels>
    <LearningStandardDocumentRefId>0FAC40650F514a459951A657F942B845</LearningStandardDocumentRefId>
    <RelatedLearningStandardItems>
      <LearningStandardItemRefId RelationshipType="childOf">FF341919CDE644998C711D756916B7E9</LearningStandardItemRefId>
    </RelatedLearningStandardItems>
  </LearningStandardItem>
  <LearningStandardItem xml:lang="en" RefID="2F4F75A169BF4c8d935F1AFAEB541601">
    <RefURI>http://corestandards.org/ELA-Literacy/SL/11-12/1/a/</RefURI>
    <StandardHierarchyLevel>
      <number>7</number>
      <description>Component</description>
    </StandardHierarchyLevel>
    <StatementCodes>
      <StatementCode>CCSS.ELA-Literacy.SL.11-12.1a</StatementCode>
    </StatementCodes>
    <Statements>
      <Statement>Come to discussions prepared, having read and researched material under study; explicitly draw on that preparation by referring to evidence from texts and other research on the topic or issue to stimulate a thoughtful, well-reasoned exchange of ideas.</Statement>
    </Statements>
    <GradeLevels>
      <GradeLevel>11-12</GradeLevel>
    </GradeLevels>
    <LearningStandardDocumentRefId>0FAC40650F514a459951A657F942B845</LearningStandardDocumentRefId>
    <RelatedLearningStandardItems>
      <LearningStandardItemRefId RelationshipType="childOf">161DCFEBB47B4046A4E8F7B551FD0B41</LearningStandardItemRefId>
    </RelatedLearningStandardItems>
  </LearningStandardItem>
  <LearningStandardItem xml:lang="en" RefID="B4FC921E642641e1BFBE63AFFFE311A3">
    <RefURI>http://corestandards.org/ELA-Literacy/SL/11-12/1/b/</RefURI>
    <StandardHierarchyLevel>
      <number>7</number>
      <description>Component</description>
    </StandardHierarchyLevel>
    <StatementCodes>
      <StatementCode>CCSS.ELA-Literacy.SL.11-12.1b</StatementCode>
    </StatementCodes>
    <Statements>
      <Statement>Work with peers to promote civil, democratic discussions and decision-making, set clear goals and deadlines, and establish individual roles as needed.</Statement>
    </Statements>
    <GradeLevels>
      <GradeLevel>11-12</GradeLevel>
    </GradeLevels>
    <LearningStandardDocumentRefId>0FAC40650F514a459951A657F942B845</LearningStandardDocumentRefId>
    <RelatedLearningStandardItems>
      <LearningStandardItemRefId RelationshipType="childOf">161DCFEBB47B4046A4E8F7B551FD0B41</LearningStandardItemRefId>
    </RelatedLearningStandardItems>
  </LearningStandardItem>
  <LearningStandardItem xml:lang="en" RefID="C0B2E6282CB442ddA731CE58EBB21CE6">
    <RefURI>http://corestandards.org/ELA-Literacy/SL/11-12/1/c/</RefURI>
    <StandardHierarchyLevel>
      <number>7</number>
      <description>Component</description>
    </StandardHierarchyLevel>
    <StatementCodes>
      <StatementCode>CCSS.ELA-Literacy.SL.11-12.1c</StatementCode>
    </StatementCodes>
    <Statements>
      <Statement>Propel conversations by posing and responding to questions that probe reasoning and evidence; ensure a hearing for a full range of positions on a topic or issue; clarify, verify, or challenge ideas and conclusions; and promote divergent and creative perspectives.</Statement>
    </Statements>
    <GradeLevels>
      <GradeLevel>11-12</GradeLevel>
    </GradeLevels>
    <LearningStandardDocumentRefId>0FAC40650F514a459951A657F942B845</LearningStandardDocumentRefId>
    <RelatedLearningStandardItems>
      <LearningStandardItemRefId RelationshipType="childOf">161DCFEBB47B4046A4E8F7B551FD0B41</LearningStandardItemRefId>
    </RelatedLearningStandardItems>
  </LearningStandardItem>
  <LearningStandardItem xml:lang="en" RefID="6ACFA2D011AB45e6943FC3B90DADFBB9">
    <RefURI>http://corestandards.org/ELA-Literacy/SL/11-12/1/d/</RefURI>
    <StandardHierarchyLevel>
      <number>7</number>
      <description>Component</description>
    </StandardHierarchyLevel>
    <StatementCodes>
      <StatementCode>CCSS.ELA-Literacy.SL.11-12.1d</StatementCode>
    </StatementCodes>
    <Statements>
      <Statement>Respond thoughtfully to diverse perspectives; synthesize comments, claims, and evidence made on all sides of an issue; resolve contradictions when possible; and determine what additional information or research is required to deepen the investigation or complete the task.</Statement>
    </Statements>
    <GradeLevels>
      <GradeLevel>11-12</GradeLevel>
    </GradeLevels>
    <LearningStandardDocumentRefId>0FAC40650F514a459951A657F942B845</LearningStandardDocumentRefId>
    <RelatedLearningStandardItems>
      <LearningStandardItemRefId RelationshipType="childOf">161DCFEBB47B4046A4E8F7B551FD0B41</LearningStandardItemRefId>
    </RelatedLearningStandardItems>
  </LearningStandardItem>
</LearningStandards>
